pytest_notifier/__init__.py
pytest_notifier/models.py
pytest_notifier/plugin.py
pytest_notifier/py.typed
pytest_notifier/settings.py
pytest_notifier/notifiers/__init__.py
pytest_notifier/notifiers/base.py
pytest_notifier/notifiers/console.py
pytest_notifier/notifiers/mattermost.py
pytest_notifier/notifiers/telegram.py
pytest_notifier_plugin-0.2.0.dist-info/METADATA
pytest_notifier_plugin-0.2.0.dist-info/WHEEL
pytest_notifier_plugin-0.2.0.dist-info/entry_points.txt
pytest_notifier_plugin-0.2.0.dist-info/RECORD
