Metadata-Version: 2.4
Name: pytest-notifier-plugin
Version: 0.2.0
Summary: Pytest plugin для отправки нотификаций в различные каналы связи о статуе прохождения тестов.
Requires-Python: >=3.13
Requires-Dist: httpx>=0.27.0
Requires-Dist: pydantic-settings>=2.6.0
Requires-Dist: pydantic>=2.7.0
Requires-Dist: pytest>=7.0
Requires-Dist: rich>=14.2.0
